BL_Python/web/__init__.py
BL_Python/web/application.py
BL_Python/web/config.py
BL_Python/web/encryption/__init__.py
BL_Python/web/host/__init__.py
BL_Python/web/middleware/__init__.py
BL_Python/web/middleware/consts.py
BL_Python/web/middleware/dependency_injection.py
BL_Python/web/middleware/sso.py
BL_Python/web/middleware/flask/__init__.py
BL_Python/web/middleware/openapi/__init__.py
BL_Python/web/middleware/openapi/cors.py
BL_Python/web/scaffolding/__init__.py
BL_Python/web/scaffolding/__main__.py
BL_Python/web/scaffolding/scaffolder.py
BL_Python/web/scaffolding/templates/base/LICENSE.md.j2
BL_Python/web/scaffolding/templates/base/README.md.j2
BL_Python/web/scaffolding/templates/base/pyproject.toml.j2
BL_Python/web/scaffolding/templates/base/docs/CONFIGURATION.md.j2
BL_Python/web/scaffolding/templates/base/{{application.module_name}}/__init__.py.j2
BL_Python/web/scaffolding/templates/base/{{application.module_name}}/__main__.py.j2
BL_Python/web/scaffolding/templates/base/{{application.module_name}}/_app_type.py.j2
BL_Python/web/scaffolding/templates/base/{{application.module_name}}/_version.py.j2
BL_Python/web/scaffolding/templates/base/{{application.module_name}}/endpoints/__init__.py.j2
BL_Python/web/scaffolding/templates/base/{{application.module_name}}/endpoints/application.py.j2
BL_Python/web/scaffolding/templates/basic/{{application.module_name}}/config.toml.j2
BL_Python/web/scaffolding/templates/openapi/{{application.module_name}}/__main__.py.j2
BL_Python/web/scaffolding/templates/openapi/{{application.module_name}}/_app_type.py.j2
BL_Python/web/scaffolding/templates/openapi/{{application.module_name}}/config.toml.j2
BL_Python/web/scaffolding/templates/openapi/{{application.module_name}}/openapi.yaml.j2
BL_Python/web/scaffolding/templates/openapi/{{application.module_name}}/endpoints/application.py.j2
BL_Python/web/scaffolding/templates/optional/{{application.module_name}}/endpoints/{{operation.module_name}}.py.j2
BL_Python.web-0.2.5.dist-info/LICENSE.md
BL_Python.web-0.2.5.dist-info/METADATA
BL_Python.web-0.2.5.dist-info/WHEEL
BL_Python.web-0.2.5.dist-info/entry_points.txt
BL_Python.web-0.2.5.dist-info/top_level.txt
BL_Python.web-0.2.5.dist-info/RECORD
